typed_argparse/__init__.py
typed_argparse/_argparse_abstractions.py
typed_argparse/arg.py
typed_argparse/choices.py
typed_argparse/exceptions.py
typed_argparse/parser.py
typed_argparse/py.typed
typed_argparse/runtime_generic.py
typed_argparse/type_utils.py
typed_argparse/typed_args.py
typed_argparse-0.3.1.dist-info/LICENSE
typed_argparse-0.3.1.dist-info/METADATA
typed_argparse-0.3.1.dist-info/WHEEL
typed_argparse-0.3.1.dist-info/top_level.txt
typed_argparse-0.3.1.dist-info/RECORD
