Metadata-Version: 2.1
Name: typed-argparse
Version: 0.3.1
Summary: Write type-safe and elegant CLIs with a clear separation of concerns.
Home-page: https://typed-argparse.github.io/typed-argparse/
Author: Fabian Keller
License: MIT
Project-URL: Source, https://github.com/typed-argparse/typed-argparse
Keywords: types
Platform: UNKNOWN
Classifier: Intended Audience :: Developers
Classifier: License :: OSI Approved :: MIT License
Classifier: Operating System :: OS Independent
Classifier: Programming Language :: Python :: 3
Classifier: Programming Language :: Python :: 3.8
Classifier: Programming Language :: Python :: 3.9
Classifier: Programming Language :: Python :: 3.10
Classifier: Programming Language :: Python :: 3.11
Requires-Python: >=3.8
Requires-Dist: typing-extensions
